Metadata-Version: 2.1
Name: lektor-gemini-capsule
Version: 0.2
Summary: Simple plugin to produce Gemini capsules with lektor.
Home-page: https://git.sr.ht/~evilham/lektor-gemini-capsule
Author: Evilham
Author-email: cvs@evilham.com
License: MIT
Keywords: Lektor plugin
Platform: UNKNOWN
Classifier: Framework :: Lektor
Classifier: Environment :: Web Environment
Classifier: Environment :: Plugins
Classifier: License :: OSI Approved :: MIT License
License-File: LICENSE
